stream_graph-0.2.0.dist-info/WHEEL
stream_graph-0.2.0.dist-info/top_level.txt
stream_graph-0.2.0.dist-info/METADATA
stream_graph-0.2.0.dist-info/RECORD
stream_graph/collections.py
stream_graph/exceptions.py
stream_graph/_c_functions.cpython-37m-x86_64-linux-gnu.so
stream_graph/__init__.py
stream_graph/base/node_set_s.py
stream_graph/base/temporal_node_set_b.py
stream_graph/base/stream_graph.py
stream_graph/base/itemporal_link_set_df.py
stream_graph/base/functions.py
stream_graph/base/link_set_df.py
stream_graph/base/itemporal_node_set_df.py
stream_graph/base/__init__.py
stream_graph/base/graph.py
stream_graph/base/temporal_link_set_df.py
stream_graph/base/multi_df_utils.py
stream_graph/base/itime_set_s.py
stream_graph/base/temporal_node_set_df.py
stream_graph/base/utils.py
stream_graph/base/time_set_df.py
stream_graph/base/dataframes/weighted_continuous_interval_df.py
stream_graph/base/dataframes/discrete_interval_df.py
stream_graph/base/dataframes/continuous_interval_df.py
stream_graph/base/dataframes/__init__.py
stream_graph/base/dataframes/weighted_instantaneous_df.py
stream_graph/base/dataframes/weighted_discrete_interval_df.py
stream_graph/base/dataframes/instantaneous_df.py
stream_graph/base/dataframes/algorithms/discrete_interval.py
stream_graph/base/dataframes/algorithms/continuous_interval.py
stream_graph/base/dataframes/algorithms/__init__.py
stream_graph/base/dataframes/algorithms/weighted_discrete_interval.py
stream_graph/base/dataframes/algorithms/weighted_instantaneous.py
stream_graph/base/dataframes/algorithms/weighted_continuous_interval.py
stream_graph/base/dataframes/algorithms/utils/__init__.py
stream_graph/base/dataframes/algorithms/utils/no_bounds.py
stream_graph/base/dataframes/algorithms/utils/bounds.py
stream_graph/base/dataframes/algorithms/utils/misc.py
stream_graph/base/dataframes/algorithms/utils/orderings.py
stream_graph/visualize/visualizer.py
stream_graph/visualize/__init__.py
stream_graph/test/test_link_set.py
stream_graph/test/test_temporal_link_set.py
stream_graph/test/test_node_set.py
stream_graph/test/__init__.py
