Metadata-Version: 2.1
Name: stream-graph
Version: 0.2.0
Summary: A library for Stream Graphs
Home-page: https://ysig.github.io/GraKeL/dev/
Author: Yiannis Siglidis [LIP6]
Author-email: Yiannis.Siglidis@lip6.fr
License: GPLv3+
Project-URL: Documentation, https://ysig.github.io/stream_graph/doc
Project-URL: Lab Website, http://www.complexnetworks.fr/
Project-URL: Source, https://github.com/ysig/stream_graph
Project-URL: Tracker, https://github.com/ysig/stream_graph/issues
Platform: UNKNOWN
Classifier: Intended Audience :: Science/Research
Classifier: Intended Audience :: Developers
Classifier: License :: OSI Approved :: GNU General Public License v3 or later (GPLv3+)
Classifier: Programming Language :: C
Classifier: Programming Language :: Python
Classifier: Topic :: Software Development
Classifier: Topic :: Sociology
Classifier: Topic :: Scientific/Engineering
Classifier: Operating System :: POSIX :: Linux
Classifier: Operating System :: MacOS
Classifier: Operating System :: Microsoft :: Windows
Classifier: Programming Language :: Python :: 2.7
Classifier: Programming Language :: Python :: 3.5
Classifier: Programming Language :: Python :: 3.6
Classifier: Programming Language :: Python :: 3.7
Requires-Python: >=2.7, !=3.0.*, !=3.1.*, !=3.2.*, !=3.3.*, !=3.4.*, <4
Provides-Extra: visualize
Requires-Dist: numpy (>=1.14.0)
Requires-Dist: pandas (>=0.22.0)
Requires-Dist: future (>=0.16.0)
Requires-Dist: six (>=1.11.0)
Requires-Dist: nose (>=1.3.0)
Requires-Dist: cython (>=0.27.3)
Provides-Extra: visualize
Requires-Dist: bokeh; extra == 'visualize'
